[{"name":"P0FiA7WWC","marks":1},{"name":"iiPdrmrw","marks":52},{"name":"PwsvKZmZV","marks":83},{"name":"LQh6aF9","marks":80},{"name":"GoqEfIYBm","marks":18},{"name":"sV","marks":28},{"name":"fk599fs5","marks":38},{"name":"psnNGzd7Q","marks":84},{"name":"uspVLyCi","marks":36},{"name":"u","marks":71},{"name":"G","marks":37},{"name":"N","marks":47},{"name":"cN","marks":99},{"name":"MX","marks":51},{"name":"Fw8jreeY","marks":67},{"name":"dM","marks":92},{"name":"W9nQKJXi","marks":82},{"name":"Xb","marks":68},{"name":"3v6MmMJZAF","marks":86},{"name":"ZaGN","marks":53},{"name":"lwSth4T2b","marks":26},{"name":"3","marks":33},{"name":"fD8851","marks":56},{"name":"AQKDRLpbl","marks":88},{"name":"4TbCXnbES","marks":93},{"name":"Zfr","marks":61},{"name":"3IA7AeOinE","marks":78},{"name":"jrvqjZF","marks":15},{"name":"MO","marks":3},{"name":"eRKW7p","marks":88},{"name":"ta6plB","marks":3},{"name":"Yvv8","marks":59},{"name":"8yVwRO","marks":53},{"name":"dStEO4B","marks":94},{"name":"fQ","marks":51},{"name":"PoZCfh42e","marks":45},{"name":"H","marks":48},{"name":"OTzEik2Z","marks":67},{"name":"msP0v7o","marks":69},{"name":"muMRbhmYxP","marks":72},{"name":"i","marks":57},{"name":"mECNY4lDwI","marks":72},{"name":"1xciq","marks":44},{"name":"j8qJhzz","marks":5},{"name":"GFJ4vfSl","marks":89},{"name":"VtGcq","marks":58},{"name":"OswWc1","marks":67},{"name":"w","marks":33},{"name":"6fxdFEBJBD","marks":23},{"name":"Z","marks":1},{"name":"Jju","marks":35},{"name":"3Tk7P","marks":0},{"name":"q0eg","marks":14},{"name":"q","marks":77},{"name":"tFLFobGW","marks":25},{"name":"lnvCAZU","marks":33},{"name":"rBD","marks":18},{"name":"DAwP1AC","marks":81},{"name":"zODBCMBOM","marks":69},{"name":"DKT2H","marks":83},{"name":"Q","marks":59},{"name":"NP72tf","marks":30},{"name":"NsJdavO","marks":0},{"name":"q7gPQewnoM","marks":37},{"name":"jtpp9Mt9H4","marks":18},{"name":"h","marks":6},{"name":"k2M3","marks":96},{"name":"Jy","marks":80},{"name":"7T1nTq","marks":50},{"name":"weWHFnP","marks":27},{"name":"qTKC","marks":17},{"name":"6dKgyo8c","marks":39},{"name":"mkRsTAU","marks":61},{"name":"CEfelgb","marks":98},{"name":"RG9EjO","marks":29},{"name":"z","marks":28},{"name":"Y1mDGs6","marks":79},{"name":"Uo","marks":71},{"name":"Cg1yReIGqA","marks":85},{"name":"6","marks":17},{"name":"xtixP7","marks":86},{"name":"OcDZyS1","marks":6},{"name":"M654WmLe1","marks":6},{"name":"o","marks":69},{"name":"hd3j","marks":36},{"name":"1pUQIX2I","marks":29},{"name":"JwiHhx","marks":90},{"name":"nzhCcGeD","marks":35},{"name":"J","marks":7},{"name":"6q8Avg16mz","marks":18},{"name":"M2d8R","marks":68},{"name":"8J","marks":11},{"name":"8c1e6IaSkT","marks":59},{"name":"vQaO","marks":5},{"name":"XVcq7z","marks":22},{"name":"sCOOi9","marks":13},{"name":"PH","marks":75},{"name":"e060I0a","marks":14},{"name":"de4IcP123w","marks":0},{"name":"wCg2Z73K","marks":97}]